{
  "kind": "collectionType",
  "collectionName": "events",
  "info": {
    "name": "Event",
    "description": ""
  },
  "options": {
    "increments": true,
    "timestamps": true,
    "draftAndPublish": true
  },
  "pluginOptions": {},
  "attributes": {
    "name": {
      "type": "string"
    },
    "description": {
      "type": "richtext"
    },
    "banner": {
      "model": "file",
      "via": "related",
      "allowedTypes": [
        "images",
        "files",
        "videos"
      ],
      "plugin": "upload",
      "required": false,
      "pluginOptions": {}
    },
    "location": {
      "type": "json"
    },
    "presentations": {
      "via": "event",
      "collection": "presentation"
    }
  }
}
